{
  "updatedAt": "2026-07-22T10:08:15.111Z",
  "comics": [
    {
      "title": "Léto, kdy umřel Hikaru 4",
      "author": "Mokumokuren",
      "cover": "https://www.obchod.crew.cz/im/coc/320/0/content/1013823/cover_image.1782138900.jpg",
      "rating": null,
      "ratingSource": null,
      "link": "https://www.databazeknih.cz/prehled-knihy/leto-kdy-umrel-hikaru-4-601093",
      "price": 199,
      "originalPrice": 249,
      "discount": 20,
      "url": "https://www.obchod.crew.cz/detail/komiks-1013823-leto-kdy-umrel-hikaru-4",
      "publisher": "CREW"
    },
    {
      "title": "Berserk 25",
      "author": "Kentaro Miura",
      "cover": "https://www.obchod.crew.cz/im/coc/320/0/content/1013788/cover_image.1779116968.jpg",
      "rating": null,
      "ratingSource": null,
      "link": "https://www.databazeknih.cz/prehled-knihy/berserk---berserk-25-599849",
      "price": 239,
      "originalPrice": 299,
      "discount": 20,
      "url": "https://www.obchod.crew.cz/detail/komiks-1013788-berserk-25",
      "publisher": "CREW"
    },
    {
      "title": "Garfield 69: Garfield nezná zbytky",
      "author": "Jim Davis",
      "cover": "https://www.obchod.crew.cz/im/coc/320/0/content/1013832/cover_image.1780669860.jpg",
      "rating": null,
      "ratingSource": null,
      "link": null,
      "price": 159,
      "originalPrice": 199,
      "discount": 20,
      "url": "https://www.obchod.crew.cz/detail/komiks-1013832-garfield-69-garfield-nezna-zbytky",
      "publisher": "CREW"
    },
    {
      "title": "Incal (brož.) (dotisk) (Mistrovská díla evropského komiksu)",
      "author": "Alejandro Jodorowsky, Moebius",
      "cover": "https://www.obchod.crew.cz/im/coc/320/0/content/529667/Incal_obalka_low.jpg",
      "rating": null,
      "ratingSource": null,
      "link": null,
      "price": 719,
      "originalPrice": 899,
      "discount": 20,
      "url": "https://www.obchod.crew.cz/detail/komiks-529667-incal-broz-dotisk-mistrovska-dila-evropskeho-komiksu",
      "publisher": "CREW"
    },
    {
      "title": "Simpsonovi 7/2026",
      "author": "Robert L. Graff, Jesse Leon McCann, Matt Groening, Oscar González Loyo, Matt Groening",
      "cover": "https://www.obchod.crew.cz/im/coc/320/0/content/1013831/cover_image.1783088386.jpg",
      "rating": 80,
      "ratingSource": "databazeknih.cz",
      "link": "https://www.databazeknih.cz/prehled-knihy/simpsonovi-bart-simpson-7-2020-432408",
      "price": 47,
      "originalPrice": 59,
      "discount": 20,
      "url": "https://www.obchod.crew.cz/detail/komiks-1013831-simpsonovi-7-2026",
      "publisher": "CREW"
    },
    {
      "title": "Star Wars: Katastrofa v káznici – Poslední mezi rovnými",
      "author": "Si Spurrier, Andrea Broccardo, Emilio Laiso, Caspar Wijngaard, Kev Walker",
      "cover": "https://www.obchod.crew.cz/im/coc/320/0/content/1013897/cover_image.1784283294.jpg",
      "rating": null,
      "ratingSource": null,
      "link": "https://www.databazeknih.cz/prehled-knihy/star-wars-komiks-katastrofa-v-kaznici-posledni-mezi-rovnymi-603332",
      "price": 629,
      "originalPrice": 699,
      "discount": 10,
      "url": "https://www.obchod.crew.cz/detail/komiks-1013897-star-wars-katastrofa-v-kaznici-posledni-mezi-rovnymi",
      "publisher": "CREW"
    },
    {
      "title": "Ostrov přátelství / Cvoci",
      "author": "Miloš Zapletal, Karel Zeman, Karel Zeman",
      "cover": "https://www.obchod.crew.cz/im/coc/320/0/content/1013894/cover_image.1784111408.jpg",
      "rating": 90,
      "ratingSource": "databazeknih.cz",
      "link": "https://www.databazeknih.cz/prehled-knihy/ostrov-pratelstvi-cvoci-598943",
      "price": 449,
      "originalPrice": 499,
      "discount": 10,
      "url": "https://www.obchod.crew.cz/detail/komiks-1013894-ostrov-pratelstvi-cvoci",
      "publisher": "CREW"
    },
    {
      "title": "One Piece 16: Pochodeň",
      "author": "Eiičiró Oda",
      "cover": "https://www.obchod.crew.cz/im/coc/320/0/content/1013822/cover_image.1780327159.jpg",
      "rating": 91,
      "ratingSource": "databazeknih.cz",
      "link": "https://www.databazeknih.cz/prehled-knihy/one-piece-romance-dawn-dobrodruzstvi-zacina-535482",
      "price": 199,
      "originalPrice": 249,
      "discount": 20,
      "url": "https://www.obchod.crew.cz/detail/komiks-1013822-one-piece-16-pochoden",
      "publisher": "CREW"
    },
    {
      "title": "Given 6",
      "author": "Nacuki Kizu",
      "cover": "https://www.obchod.crew.cz/im/coc/320/0/content/1013821/cover_image.1780327057.jpg",
      "rating": null,
      "ratingSource": null,
      "link": "https://www.databazeknih.cz/prehled-knihy/given-given-6-601088",
      "price": 199,
      "originalPrice": 249,
      "discount": 20,
      "url": "https://www.obchod.crew.cz/detail/komiks-1013821-given-6",
      "publisher": "CREW"
    },
    {
      "title": "Dandadan 8",
      "author": "Jukinobu Tacu",
      "cover": "https://www.obchod.crew.cz/im/coc/320/0/content/1013834/cover_image.1780670002.jpg",
      "rating": 100,
      "ratingSource": "databazeknih.cz",
      "link": "https://www.databazeknih.cz/prehled-knihy/dandadan-dandadan-8-601354",
      "price": 199,
      "originalPrice": 249,
      "discount": 20,
      "url": "https://www.obchod.crew.cz/detail/komiks-1013834-dandadan-8",
      "publisher": "CREW"
    },
    {
      "title": "Batman / Deadpool",
      "author": "Zeb Wells, James Tynion IV, Joshua Williamson, Tom Taylor, Mariko Tamaki, Scott Snyder, G. Willow Wilsonová, Grant Morrison, Greg Capullo, Bruno Redondo, Dan Mora, Amanda Connerová, Hayden Sherman, Denys Cowan",
      "cover": "https://www.obchod.crew.cz/im/coc/320/0/content/1013783/cover_image.1778772921.jpg",
      "rating": 83,
      "ratingSource": "databazeknih.cz",
      "link": "https://www.databazeknih.cz/prehled-knihy/batman-deadpool-603020",
      "price": 343,
      "originalPrice": 429,
      "discount": 20,
      "url": "https://www.obchod.crew.cz/detail/komiks-1013783-batman-deadpool",
      "publisher": "CREW"
    }
  ],
  "bestsellers": [
    {
      "title": "One Piece 16: Pochodeň",
      "author": "Eiičiró Oda",
      "cover": "https://www.obchod.crew.cz/im/coc/320/0/content/1013822/cover_image.1780327159.jpg",
      "rating": 91,
      "ratingSource": "databazeknih.cz",
      "link": "https://www.databazeknih.cz/prehled-knihy/one-piece-romance-dawn-dobrodruzstvi-zacina-535482",
      "price": 199,
      "originalPrice": 249,
      "discount": 20,
      "url": "https://www.obchod.crew.cz/detail/komiks-1013822-one-piece-16-pochoden",
      "publisher": "CREW"
    },
    {
      "title": "Ateliér špičatých klobouků 14",
      "author": "Kamome Širahama",
      "cover": "https://www.obchod.crew.cz/im/coc/320/0/content/1013787/cover_image.1779116894.jpg",
      "rating": 100,
      "ratingSource": "databazeknih.cz",
      "link": "https://www.databazeknih.cz/prehled-knihy/atelier-spicatych-klobouku-atelier-spicatych-klobouku-14-599851",
      "price": 224,
      "originalPrice": 249,
      "discount": 10,
      "url": "https://www.obchod.crew.cz/detail/komiks-1013787-atelier-spicatych-klobouku-14",
      "publisher": "CREW"
    },
    {
      "title": "Berserk 25",
      "author": "Kentaro Miura",
      "cover": "https://www.obchod.crew.cz/im/coc/320/0/content/1013788/cover_image.1779116968.jpg",
      "rating": null,
      "ratingSource": null,
      "link": "https://www.databazeknih.cz/prehled-knihy/berserk---berserk-25-599849",
      "price": 239,
      "originalPrice": 299,
      "discount": 20,
      "url": "https://www.obchod.crew.cz/detail/komiks-1013788-berserk-25",
      "publisher": "CREW"
    },
    {
      "title": "Strýček Skrblík: Jen chudý stařík",
      "author": "Carl Barks",
      "cover": "https://www.obchod.crew.cz/im/coc/320/0/content/1013794/cover_image.1779118743.jpg",
      "rating": 94,
      "ratingSource": "databazeknih.cz",
      "link": "https://www.databazeknih.cz/prehled-knihy/strycek-skrblik-jen-chudy-starik-600171",
      "price": 719,
      "originalPrice": 799,
      "discount": 10,
      "url": "https://www.obchod.crew.cz/detail/komiks-1013794-strycek-skrblik-jen-chudy-starik",
      "publisher": "CREW"
    },
    {
      "title": "Batman / Deadpool",
      "author": "Zeb Wells, James Tynion IV, Joshua Williamson, Tom Taylor, Mariko Tamaki, Scott Snyder, G. Willow Wilsonová, Grant Morrison, Greg Capullo, Bruno Redondo, Dan Mora, Amanda Connerová, Hayden Sherman, Denys Cowan",
      "cover": "https://www.obchod.crew.cz/im/coc/320/0/content/1013783/cover_image.1778772921.jpg",
      "rating": 83,
      "ratingSource": "databazeknih.cz",
      "link": "https://www.databazeknih.cz/prehled-knihy/batman-deadpool-603020",
      "price": 343,
      "originalPrice": 429,
      "discount": 20,
      "url": "https://www.obchod.crew.cz/detail/komiks-1013783-batman-deadpool",
      "publisher": "CREW"
    },
    {
      "title": "Dandadan 8",
      "author": "Jukinobu Tacu",
      "cover": "https://www.obchod.crew.cz/im/coc/320/0/content/1013834/cover_image.1780670002.jpg",
      "rating": 100,
      "ratingSource": "databazeknih.cz",
      "link": "https://www.databazeknih.cz/prehled-knihy/dandadan-dandadan-8-601354",
      "price": 199,
      "originalPrice": 249,
      "discount": 20,
      "url": "https://www.obchod.crew.cz/detail/komiks-1013834-dandadan-8",
      "publisher": "CREW"
    },
    {
      "title": "Láska ve střihu cosplaye 14",
      "author": "Šin'iči Fukuda",
      "cover": "https://www.obchod.crew.cz/im/coc/320/0/content/1013789/cover_image.1779117040.jpg",
      "rating": 98,
      "ratingSource": "databazeknih.cz",
      "link": "https://www.databazeknih.cz/prehled-knihy/laska-ve-strihu-cosplaye-laska-ve-strihu-cosplaye-14-599850",
      "price": 224,
      "originalPrice": 249,
      "discount": 10,
      "url": "https://www.obchod.crew.cz/detail/komiks-1013789-laska-ve-strihu-cosplaye-14",
      "publisher": "CREW"
    },
    {
      "title": "Made in Abyss - Stvořen v Propasti 3",
      "author": "Akihito Cukuši",
      "cover": "https://www.obchod.crew.cz/im/coc/320/0/content/1013795/cover_image.1779118816.jpg",
      "rating": 94,
      "ratingSource": "databazeknih.cz",
      "link": "https://www.databazeknih.cz/prehled-knihy/made-in-abyss-stvoren-v-propasti-3-599862",
      "price": 224,
      "originalPrice": 249,
      "discount": 10,
      "url": "https://www.obchod.crew.cz/detail/komiks-1013795-made-in-abyss-stvoren-v-propasti-3",
      "publisher": "CREW"
    },
    {
      "title": "Zaklínač: Medvěd a motýl",
      "author": "Simon Spurrier, Stephen Green",
      "cover": "https://www.obchod.crew.cz/im/coc/320/0/content/1013784/cover_image.1778773108.jpg",
      "rating": 85,
      "ratingSource": "databazeknih.cz",
      "link": "https://www.databazeknih.cz/prehled-knihy/zaklinac-medved-a-motyl-601306",
      "price": 314,
      "originalPrice": 349,
      "discount": 10,
      "url": "https://www.obchod.crew.cz/detail/komiks-1013784-zaklinac-medved-a-motyl",
      "publisher": "CREW"
    },
    {
      "title": "One-Punch Man 18: Omezovač",
      "author": "ONE, Júsuke Murata",
      "cover": "https://www.obchod.crew.cz/im/coc/320/0/content/1013682/cover_image.1773410551.jpg",
      "rating": 85,
      "ratingSource": "databazeknih.cz",
      "link": "https://www.databazeknih.cz/prehled-knihy/one-punch-man-az-na-doraz-578053",
      "price": 242,
      "originalPrice": 269,
      "discount": 10,
      "url": "https://www.obchod.crew.cz/detail/komiks-1013682-one-punch-man-18-omezovac",
      "publisher": "CREW"
    },
    {
      "title": "Poison City",
      "author": "Tecuja Cucui",
      "cover": "https://www.obchod.crew.cz/im/coc/320/0/content/1013790/cover_image.1779117237.jpg",
      "rating": 80,
      "ratingSource": "databazeknih.cz",
      "link": "https://www.databazeknih.cz/prehled-knihy/poison-city-600011",
      "price": 449,
      "originalPrice": 499,
      "discount": 10,
      "url": "https://www.obchod.crew.cz/detail/komiks-1013790-poison-city",
      "publisher": "CREW"
    },
    {
      "title": "Kagurabači 4: Rovnost",
      "author": "Takeru Hokazono",
      "cover": "https://www.obchod.crew.cz/im/coc/320/0/content/1013818/cover_image.1780326781.jpg",
      "rating": 95,
      "ratingSource": "databazeknih.cz",
      "link": "https://www.databazeknih.cz/prehled-knihy/kagurabaci-rovnost-601090",
      "price": 224,
      "originalPrice": 249,
      "discount": 10,
      "url": "https://www.obchod.crew.cz/detail/komiks-1013818-kagurabaci-4-rovnost",
      "publisher": "CREW"
    },
    {
      "title": "Ďábel v detailu 1",
      "author": "Stjepan Šejić",
      "cover": "https://www.obchod.crew.cz/im/coc/320/0/content/1013793/cover_image.1779118539.jpg",
      "rating": 92,
      "ratingSource": "databazeknih.cz",
      "link": "https://www.databazeknih.cz/prehled-knihy/dabel-v-detailu-kniha-prvni-600012",
      "price": 422,
      "originalPrice": 469,
      "discount": 10,
      "url": "https://www.obchod.crew.cz/detail/komiks-1013793-dabel-v-detailu-1",
      "publisher": "CREW"
    },
    {
      "title": "Útok titánů: Ztracené dívky 2",
      "author": "Hadžime Isajama, Hiroši Seko, Rjósuke Fudži, Rjósuke Fudži",
      "cover": "https://www.obchod.crew.cz/im/coc/320/0/content/1013797/cover_image.1779118972.jpg",
      "rating": 80,
      "ratingSource": "databazeknih.cz",
      "link": "https://www.databazeknih.cz/prehled-knihy/utok-titanu-ztracene-divky---utok-titanu-ztracene-divky-2-599853",
      "price": 206,
      "originalPrice": 229,
      "discount": 10,
      "url": "https://www.obchod.crew.cz/detail/komiks-1013797-utok-titanu-ztracene-divky-2",
      "publisher": "CREW"
    },
    {
      "title": "Naušika z Větrného údolí 2",
      "author": "Hajao Mijazaki",
      "cover": "https://www.obchod.crew.cz/im/coc/320/0/content/1013675/cover_image.1773408674.jpg",
      "rating": 87,
      "ratingSource": "databazeknih.cz",
      "link": "https://www.databazeknih.cz/prehled-knihy/nausika-z-vetrneho-udoli-2-595129",
      "price": 269,
      "originalPrice": 299,
      "discount": 10,
      "url": "https://www.obchod.crew.cz/detail/komiks-1013675-nausika-z-vetrneho-udoli-2",
      "publisher": "CREW"
    },
    {
      "title": "Jak jsem se reinkarnoval coby sliz 17",
      "author": "Fuse, Taiki Kawakami",
      "cover": "https://www.obchod.crew.cz/im/coc/320/0/content/1013779/cover_image.1778768973.jpg",
      "rating": 93,
      "ratingSource": "databazeknih.cz",
      "link": "https://www.databazeknih.cz/prehled-knihy/jak-jsem-se-reinkarnoval-coby-sliz-jak-jsem-se-reinkarnoval-coby-sliz-17-600738",
      "price": 224,
      "originalPrice": 249,
      "discount": 10,
      "url": "https://www.obchod.crew.cz/detail/komiks-1013779-jak-jsem-se-reinkarnoval-coby-sliz-17",
      "publisher": "CREW"
    },
    {
      "title": "Sakamoto Days 12: Točíme",
      "author": "Júto Suzuki",
      "cover": "https://www.obchod.crew.cz/im/coc/320/0/content/1013781/cover_image.1780310213.jpg",
      "rating": 87,
      "ratingSource": "databazeknih.cz",
      "link": "https://www.databazeknih.cz/prehled-knihy/sakamoto-days-legendarni-zabijak-514302",
      "price": 224,
      "originalPrice": 249,
      "discount": 10,
      "url": "https://www.obchod.crew.cz/detail/komiks-1013781-sakamoto-days-12-tocime",
      "publisher": "CREW"
    },
    {
      "title": "AARGH! 25 (růžová obálka)",
      "author": "Různí",
      "cover": "https://www.obchod.crew.cz/im/coc/320/0/content/1013845/cover_image.1781095039.jpg",
      "rating": null,
      "ratingSource": null,
      "link": null,
      "price": 224,
      "originalPrice": 249,
      "discount": 10,
      "url": "https://www.obchod.crew.cz/detail/komiks-1013845-aargh-25-ruzova-obalka",
      "publisher": "CREW"
    },
    {
      "title": "Netvora 9: Posedlí",
      "author": "Marjorie Liu, Sana Takeda",
      "cover": "https://www.obchod.crew.cz/im/coc/320/0/content/1013813/cover_image.1780324200.jpg",
      "rating": 90,
      "ratingSource": "databazeknih.cz",
      "link": "https://www.databazeknih.cz/prehled-knihy/netvora-posedli-601091",
      "price": 449,
      "originalPrice": 499,
      "discount": 10,
      "url": "https://www.obchod.crew.cz/detail/komiks-1013813-netvora-9-posedli",
      "publisher": "CREW"
    },
    {
      "title": "[Moje hvězda] 10",
      "author": "Aka Akasaka, Mengo Jokojari",
      "cover": "https://www.obchod.crew.cz/im/coc/320/0/content/1013819/cover_image.1780326866.jpg",
      "rating": 90,
      "ratingSource": "databazeknih.cz",
      "link": "https://www.databazeknih.cz/prehled-knihy/moje-hvezda-moje-hvezda-10-601087",
      "price": 224,
      "originalPrice": 249,
      "discount": 10,
      "url": "https://www.obchod.crew.cz/detail/komiks-1013819-moje-hvezda-10",
      "publisher": "CREW"
    },
    {
      "title": "Naruto 72: Naruto Uzumaki",
      "author": "Masaši Kišimoto",
      "cover": "https://www.obchod.crew.cz/im/coc/320/0/content/1013780/cover_image.1778769076.jpg",
      "rating": 88,
      "ratingSource": "databazeknih.cz",
      "link": "https://www.databazeknih.cz/prehled-knihy/naruto-naruto-uzumaki-84672",
      "price": 206,
      "originalPrice": 229,
      "discount": 10,
      "url": "https://www.obchod.crew.cz/detail/komiks-1013780-naruto-72-naruto-uzumaki",
      "publisher": "CREW"
    },
    {
      "title": "One Piece 15: Kupředu!",
      "author": "Eiičiró Oda",
      "cover": "https://www.obchod.crew.cz/im/coc/320/0/content/1013713/cover_image.1775654560.jpg",
      "rating": 91,
      "ratingSource": "databazeknih.cz",
      "link": "https://www.databazeknih.cz/prehled-knihy/one-piece-romance-dawn-dobrodruzstvi-zacina-535482",
      "price": 224,
      "originalPrice": 249,
      "discount": 10,
      "url": "https://www.obchod.crew.cz/detail/komiks-1013713-one-piece-15-kupredu",
      "publisher": "CREW"
    },
    {
      "title": "SpongeBob 7/2026",
      "author": "Corey Barba, James Kochalka, Sam Henderson, Robert Leighton, Richard Pursel, Dean Haspiel, Corey Barba, Joey Weiser, Gregg Schigiel, Scott Roberts, Jacob Chabot, James Kochalka",
      "cover": "https://www.obchod.crew.cz/im/coc/320/0/content/1013816/cover_image.1780325835.jpg",
      "rating": 70,
      "ratingSource": "databazeknih.cz",
      "link": "https://www.databazeknih.cz/prehled-knihy/spongebob-a-filozofie-201484",
      "price": 53,
      "originalPrice": 59,
      "discount": 10,
      "url": "https://www.obchod.crew.cz/detail/komiks-1013816-spongebob-7-2026",
      "publisher": "CREW"
    },
    {
      "title": "Kapesní komiksové klenoty: Supergirl: Dívka z Kryptonu",
      "author": "Otto Binder, Jeph Loeb, Michael Turner, Al Plastino",
      "cover": "https://www.obchod.crew.cz/im/coc/320/0/content/1013807/cover_image.1779959796.jpg",
      "rating": 90,
      "ratingSource": "databazeknih.cz",
      "link": "https://www.databazeknih.cz/prehled-knihy/kapesni-komiksove-klenoty---supergirl-divka-z-kryptonu-603241",
      "price": 179,
      "originalPrice": 199,
      "discount": 10,
      "url": "https://www.obchod.crew.cz/detail/komiks-1013807-kapesni-komiksove-klenoty-supergirl-divka-z-kryptonu",
      "publisher": "CREW"
    },
    {
      "title": "Batman - Legendy Temného rytíře: Šílenství / Nákaza",
      "author": "Warren Ellis, Garth Ennis, Will Simpson, John McCrea",
      "cover": "https://www.obchod.crew.cz/im/coc/320/0/content/1013778/cover_image.1778768445.jpg",
      "rating": 64,
      "ratingSource": "databazeknih.cz",
      "link": "https://www.databazeknih.cz/prehled-knihy/batman-legendy-temneho-rytire-silenstvi-nakaza-599671",
      "price": 314,
      "originalPrice": 349,
      "discount": 10,
      "url": "https://www.obchod.crew.cz/detail/komiks-1013778-batman-legendy-temneho-rytire-silenstvi-nakaza",
      "publisher": "CREW"
    },
    {
      "title": "Delicious in Dungeon - Chuť podzemí 1",
      "author": "Rjóko Kui",
      "cover": "https://www.obchod.crew.cz/im/coc/320/0/content/1013748/cover_image.1776870100.jpg",
      "rating": 85,
      "ratingSource": "databazeknih.cz",
      "link": "https://www.databazeknih.cz/prehled-knihy/delicious-in-dungeon-chut-podzemi-delicious-in-dungeon-chut-podzemi-1-598473",
      "price": 224,
      "originalPrice": 249,
      "discount": 10,
      "url": "https://www.obchod.crew.cz/detail/komiks-1013748-delicious-in-dungeon-chut-podzemi-1",
      "publisher": "CREW"
    },
    {
      "title": "Léto, kdy umřel Hikaru 4",
      "author": "Mokumokuren",
      "cover": "https://www.obchod.crew.cz/im/coc/320/0/content/1013823/cover_image.1782138900.jpg",
      "rating": null,
      "ratingSource": null,
      "link": "https://www.databazeknih.cz/prehled-knihy/leto-kdy-umrel-hikaru-4-601093",
      "price": 199,
      "originalPrice": 249,
      "discount": 20,
      "url": "https://www.obchod.crew.cz/detail/komiks-1013823-leto-kdy-umrel-hikaru-4",
      "publisher": "CREW"
    },
    {
      "title": "Legenda o Sim Čchong 4",
      "author": "seri, Biwan",
      "cover": "https://www.obchod.crew.cz/im/coc/320/0/content/1013815/cover_image.1780324380.jpg",
      "rating": 95,
      "ratingSource": "databazeknih.cz",
      "link": "https://www.databazeknih.cz/prehled-knihy/legenda-o-sim-cchong-legenda-o-sim-cchong-4-601089",
      "price": 359,
      "originalPrice": 399,
      "discount": 10,
      "url": "https://www.obchod.crew.cz/detail/komiks-1013815-legenda-o-sim-cchong-4",
      "publisher": "CREW"
    },
    {
      "title": "Zrádné tropy (Velké evropské komiksy) (základní verze)",
      "author": "Alain Ayroles, Juanjo Guarnido",
      "cover": "https://www.obchod.crew.cz/im/coc/320/0/content/1013750/cover_image.1777021884.jpg",
      "rating": null,
      "ratingSource": null,
      "link": null,
      "price": 599,
      "originalPrice": null,
      "discount": 0,
      "url": "https://www.obchod.crew.cz/detail/komiks-1013750-zradne-tropy-velke-evropske-komiksy-zakladni-verze",
      "publisher": "CREW"
    },
    {
      "title": "Cizinec v jarním vánku 3",
      "author": "Kanna Kii",
      "cover": "https://www.obchod.crew.cz/im/coc/320/0/content/1013734/cover_image.1776096196.jpg",
      "rating": 84,
      "ratingSource": "databazeknih.cz",
      "link": "https://www.databazeknih.cz/prehled-knihy/cizinec-v-jarnim-vanku-3-597282",
      "price": 224,
      "originalPrice": 249,
      "discount": 10,
      "url": "https://www.obchod.crew.cz/detail/komiks-1013734-cizinec-v-jarnim-vanku-3",
      "publisher": "CREW"
    }
  ]
}