{
  "updatedAt": "2026-07-04T06:58:48.486Z",
  "items": [
    {
      "type": "book",
      "title": "Pomalost",
      "author": "Milan Kundera",
      "cover": "https://obalky.kosmas.cz/ArticleCovers/569/067_bg.jpg",
      "rating": 78,
      "ratingSource": "databazeknih.cz",
      "link": "https://www.databazeknih.cz/prehled-knihy/pomalost-600980",
      "price": 297,
      "priceShop": "Kosmas",
      "cat": [
        "Kosmas"
      ],
      "firstSeen": "2026-07-02",
      "daysLeft": 1
    },
    {
      "type": "book",
      "title": "Kronika",
      "author": "Dětmar z Merseburku",
      "cover": "https://obalky.kosmas.cz/ArticleCovers/121/826_bg.jpg",
      "rating": 90,
      "ratingSource": "databazeknih.cz",
      "link": "https://www.databazeknih.cz/prehled-knihy/kronika-36159",
      "price": 423,
      "priceShop": "Kosmas",
      "cat": [
        "Kosmas"
      ],
      "firstSeen": "2026-07-02",
      "daysLeft": 1
    },
    {
      "type": "book",
      "title": "Marek Dvořák: Už letím",
      "author": "Martin Moravec",
      "cover": "https://obalky.kosmas.cz/ArticleCovers/569/396_bg.jpg",
      "rating": 97,
      "ratingSource": "databazeknih.cz",
      "link": "https://www.databazeknih.cz/prehled-knihy/uz-letim-599493",
      "price": 386,
      "priceShop": "Kosmas",
      "cat": [
        "Kosmas"
      ],
      "firstSeen": "2026-07-02",
      "daysLeft": 1
    },
    {
      "type": "book",
      "title": "Neznají strach",
      "author": "Christian Dunn",
      "cover": "https://obalky.kosmas.cz/ArticleCovers/570/413_bg.jpg",
      "rating": 90,
      "ratingSource": "databazeknih.cz",
      "link": "https://www.databazeknih.cz/prehled-knihy/warhammer-40-000-horovo-kacirstvi---neznaji-strach-601746",
      "price": 377,
      "priceShop": "Kosmas",
      "cat": [
        "Kosmas"
      ],
      "firstSeen": "2026-07-02",
      "daysLeft": 1
    },
    {
      "type": "book",
      "title": "O tom Benešovi",
      "author": "Pavel Kosatík",
      "cover": "https://obalky.kosmas.cz/ArticleCovers/556/453_bg.jpg",
      "rating": null,
      "ratingSource": "databazeknih.cz",
      "link": "https://www.databazeknih.cz/",
      "price": 539,
      "priceShop": "Kosmas",
      "cat": [
        "Kosmas"
      ],
      "firstSeen": "2026-07-02",
      "daysLeft": 1
    },
    {
      "type": "book",
      "title": "Paměti",
      "author": "Farah Pahlaví",
      "cover": "https://obalky.kosmas.cz/ArticleCovers/568/841_bg.jpg",
      "rating": 90,
      "ratingSource": "databazeknih.cz",
      "link": "https://www.databazeknih.cz/prehled-knihy/pameti-3096",
      "price": 529,
      "priceShop": "Kosmas",
      "cat": [
        "Kosmas"
      ],
      "firstSeen": "2026-07-02",
      "daysLeft": 1
    },
    {
      "type": "book",
      "title": "Putinovi žoldnéři 2013–24",
      "author": "Mark Galeotti",
      "cover": "https://obalky.kosmas.cz/ArticleCovers/569/955_bg.jpg",
      "rating": null,
      "ratingSource": "databazeknih.cz",
      "link": "https://www.databazeknih.cz/prehled-knihy/putinovi-zoldneri-2013-2024-wagnerova-skupina-a-dalsi-ruske-soukrome-vojenske-spolecnosti-601614",
      "price": 242,
      "priceShop": "Kosmas",
      "cat": [
        "Kosmas"
      ],
      "firstSeen": "2026-07-02",
      "daysLeft": 1
    },
    {
      "type": "book",
      "title": "Typo života běh = Solpera",
      "author": "Jan Solpera",
      "cover": "https://obalky.kosmas.cz/ArticleCovers/566/733_bg.jpg",
      "rating": null,
      "ratingSource": "databazeknih.cz",
      "link": "https://www.databazeknih.cz/prehled-knihy/typo-zivota-beh-solpera-603058",
      "price": 495,
      "priceShop": "Kosmas",
      "cat": [
        "Kosmas"
      ],
      "firstSeen": "2026-07-02",
      "daysLeft": 1
    },
    {
      "type": "book",
      "title": "Velké dějiny zemí Koruny české XIX., 1968",
      "author": "Jiří Hoppe",
      "cover": "https://obalky.kosmas.cz/ArticleCovers/564/102_bg.jpg",
      "rating": null,
      "ratingSource": "databazeknih.cz",
      "link": "https://www.databazeknih.cz/prehled-knihy/velke-dejiny-zemi-koruny-ceske-velke-dejiny-zemi-koruny-ceske-svazek-xix-1968-592075",
      "price": 801,
      "priceShop": "Kosmas",
      "cat": [
        "Kosmas"
      ],
      "firstSeen": "2026-07-02",
      "daysLeft": 1
    },
    {
      "type": "book",
      "title": "Pobřeží seskvečů",
      "author": "Eden Robinsonová",
      "cover": "https://obalky.kosmas.cz/ArticleCovers/192/960_bg.jpg",
      "rating": 86,
      "ratingSource": "databazeknih.cz",
      "link": "https://www.databazeknih.cz/prehled-knihy/pobrezi-seskvecu-202204",
      "price": 26,
      "priceShop": "Kosmas",
      "cat": [
        "Kosmas"
      ],
      "firstSeen": "2026-07-02",
      "daysLeft": 1
    },
    {
      "type": "book",
      "title": "Zoufalství",
      "author": "Yasmina Reza",
      "cover": "https://obalky.kosmas.cz/ArticleCovers/132/496_bg.jpg",
      "rating": 60,
      "ratingSource": "databazeknih.cz",
      "link": "https://www.databazeknih.cz/prehled-knihy/zoufalstvi-15138",
      "price": 29,
      "priceShop": "Kosmas",
      "cat": [
        "Kosmas"
      ],
      "firstSeen": "2026-07-02",
      "daysLeft": 1
    },
    {
      "type": "book",
      "title": "Aby vzpomínky nevybledly jako číslo na mém předloktí",
      "author": "Nicolas Büchse",
      "cover": "https://obalky.kosmas.cz/ArticleCovers/566/998_bg.jpg",
      "rating": 95,
      "ratingSource": "databazeknih.cz",
      "link": "https://www.databazeknih.cz/prehled-knihy/aby-vzpominky-nevybledly-jako-cislo-na-mem-predlokti-skutecny-pribeh-o-holocaustu-preziti-a-jednom-slibu-ktery-pretrva-veky-598477",
      "price": 449,
      "priceShop": "Kosmas",
      "cat": [
        "Kosmas"
      ],
      "firstSeen": "2026-07-02",
      "daysLeft": 1
    },
    {
      "type": "book",
      "title": "Anglicko-český a česko-anglický Praktický slovník",
      "author": "kolektiv autorů",
      "cover": "https://obalky.kosmas.cz/ArticleCovers/569/248_bg.jpg",
      "rating": 93,
      "ratingSource": "databazeknih.cz",
      "link": "https://www.databazeknih.cz/prehled-knihy/anglicko-cesky-cesko-anglicky-slovnik-s-anglickou-vyslovnosti-v-obou-castech-31561",
      "price": 531,
      "priceShop": "Kosmas",
      "cat": [
        "Kosmas"
      ],
      "firstSeen": "2026-07-02",
      "daysLeft": 1
    },
    {
      "type": "book",
      "title": "Antimemetická divize neexistuje",
      "author": "Sam Hughes",
      "cover": "https://obalky.kosmas.cz/ArticleCovers/570/355_bg.jpg",
      "rating": 73,
      "ratingSource": "databazeknih.cz",
      "link": "https://www.databazeknih.cz/prehled-knihy/antimemeticka-divize-neexistuje-602751",
      "price": 323,
      "priceShop": "Kosmas",
      "cat": [
        "Kosmas"
      ],
      "firstSeen": "2026-07-02",
      "daysLeft": 1
    },
    {
      "type": "book",
      "title": "Babička, která projela svět na kole",
      "author": "Gabri Ródenas",
      "cover": "https://obalky.kosmas.cz/ArticleCovers/568/223_bg.jpg",
      "rating": null,
      "ratingSource": "databazeknih.cz",
      "link": "https://www.databazeknih.cz/prehled-knihy/babicka-ktera-projela-svet-na-kole-597349",
      "price": 314,
      "priceShop": "Kosmas",
      "cat": [
        "Kosmas"
      ],
      "firstSeen": "2026-07-02",
      "daysLeft": 1
    },
    {
      "type": "book",
      "title": "Bílý tesák",
      "author": "Jack London",
      "cover": "https://obalky.kosmas.cz/ArticleCovers/568/224_bg.jpg",
      "rating": 89,
      "ratingSource": "databazeknih.cz",
      "link": "https://www.databazeknih.cz/prehled-knihy/bily-tesak-8519",
      "price": 359,
      "priceShop": "Kosmas",
      "cat": [
        "Kosmas"
      ],
      "firstSeen": "2026-07-02",
      "daysLeft": 1
    },
    {
      "type": "book",
      "title": "Srdceboly",
      "author": "Simona Monyová",
      "cover": "https://www.knihydobrovsky.cz/thumbs/og-image/mod_eshop/produkty/803547108/srdceboly-1.jpg",
      "rating": 77,
      "ratingSource": "databazeknih.cz",
      "link": "https://www.databazeknih.cz/prehled-knihy/srdceboly-79247",
      "price": 151,
      "priceShop": "Dobrovský",
      "cat": [
        "Dobrovský"
      ],
      "firstSeen": "2026-07-02",
      "daysLeft": 1
    },
    {
      "type": "movie",
      "title": "Enola Holmesová 3",
      "year": "2026",
      "rating": 52,
      "poster": "https://image.pmgstatic.com/cache/resized/w936/files/images/film/photos/171/420/171420248_y32myb.jpg",
      "url": "https://www.csfd.cz/film/1691342-enola-holmesova-3/prehled/",
      "genres": [
        "Drama",
        "Krimi"
      ],
      "country": "USA",
      "vod": [
        "Netflix"
      ],
      "csfdType": "film",
      "firstSeen": "2026-07-02",
      "daysLeft": 1
    },
    {
      "type": "movie",
      "title": "Pozvání",
      "year": "2026",
      "rating": 78,
      "poster": "https://image.pmgstatic.com/cache/resized/w936/files/images/film/photos/170/915/170915505_n13g6d.jpg",
      "url": "https://www.csfd.cz/film/1670293-pozvani/prehled/",
      "genres": [
        "Komedie",
        "Drama"
      ],
      "country": "USA",
      "vod": [
        "Kino"
      ],
      "csfdType": "film",
      "firstSeen": "2026-07-02",
      "daysLeft": 1
    },
    {
      "type": "series",
      "title": "Země gangů",
      "year": "2025",
      "rating": 87,
      "poster": "https://image.pmgstatic.com/cache/resized/h125/files/images/film/posters/170/410/170410515_x8vh6i.png",
      "url": "https://www.csfd.cz/film/1644096-zeme-gangu/prehled/",
      "genres": [
        "Krimi",
        "Drama"
      ],
      "country": "USA",
      "vod": [
        "SkyShowtime"
      ],
      "csfdType": "seriál",
      "firstSeen": "2026-07-02",
      "daysLeft": 1
    },
    {
      "type": "game",
      "title": "Feed The Pit",
      "rating": 100,
      "reviews": 61,
      "scoreDesc": "Very Positive",
      "price": "9,22€",
      "image": "https://shared.cloudflare.steamstatic.com/store_item_assets/steam/apps/3278290/header.jpg?t=1782889032",
      "url": "https://store.steampowered.com/app/3278290/",
      "tags": [
        "Akční",
        "Nezávislé"
      ],
      "released": "2026-06-30T00:00:00.000Z",
      "firstSeen": "2026-07-02",
      "daysLeft": 1
    },
    {
      "type": "book",
      "title": "Město a jeho nejisté zdi",
      "author": "Haruki Murakami",
      "cover": "https://obalky.kosmas.cz/ArticleCovers/567/410_bg.jpg",
      "rating": 89,
      "ratingSource": "databazeknih.cz",
      "link": "https://www.databazeknih.cz/prehled-knihy/rodina-snopesu-mesto-48052",
      "price": 629,
      "priceShop": "Kosmas",
      "cat": [
        "Kosmas"
      ],
      "firstSeen": "2026-07-03",
      "daysLeft": 2
    },
    {
      "type": "book",
      "title": "GLP-1 kuchařka",
      "author": "Evžen Machytka",
      "cover": "https://obalky.kosmas.cz/ArticleCovers/566/097_bg.jpg",
      "rating": null,
      "ratingSource": "databazeknih.cz",
      "link": "https://www.databazeknih.cz/prehled-knihy/glp-1-kucharka-dr-evzen-vari-uzivatelum-leku-na-hubnuti-594833",
      "price": 449,
      "priceShop": "Kosmas",
      "cat": [
        "Kosmas"
      ],
      "firstSeen": "2026-07-03",
      "daysLeft": 2
    },
    {
      "type": "book",
      "title": "Adam Haberberg",
      "author": "Yasmina Reza",
      "cover": "https://obalky.kosmas.cz/ArticleCovers/159/610_bg.jpg",
      "rating": 70,
      "ratingSource": "databazeknih.cz",
      "link": "https://www.databazeknih.cz/prehled-knihy/adam-haberberg-71214",
      "price": 26,
      "priceShop": "Kosmas",
      "cat": [
        "Kosmas"
      ],
      "firstSeen": "2026-07-03",
      "daysLeft": 2
    },
    {
      "type": "book",
      "title": "Jsem tu novej",
      "author": "Matt Field",
      "cover": "https://obalky.kosmas.cz/ArticleCovers/553/841_bg.jpg",
      "rating": 81,
      "ratingSource": "databazeknih.cz",
      "link": "https://www.databazeknih.cz/prehled-knihy/jsem-tu-novej-594447",
      "price": 449,
      "priceShop": "Kosmas",
      "cat": [
        "Kosmas"
      ],
      "firstSeen": "2026-07-03",
      "daysLeft": 2
    },
    {
      "type": "book",
      "title": "Lázár",
      "author": "Nelio Biedermann",
      "cover": "https://obalky.kosmas.cz/ArticleCovers/565/130_bg.jpg",
      "rating": 80,
      "ratingSource": "databazeknih.cz",
      "link": "https://www.databazeknih.cz/prehled-knihy/lazar-99864",
      "price": 447,
      "priceShop": "Kosmas",
      "cat": [
        "Kosmas"
      ],
      "firstSeen": "2026-07-03",
      "daysLeft": 2
    },
    {
      "type": "book",
      "title": "Spravedlivý růst",
      "author": "Daniel Prokop",
      "cover": "https://obalky.kosmas.cz/ArticleCovers/557/209_bg.jpg",
      "rating": 97,
      "ratingSource": "databazeknih.cz",
      "link": "https://www.databazeknih.cz/prehled-knihy/spravedlivy-rust-602380",
      "price": 494,
      "priceShop": "Kosmas",
      "cat": [
        "Kosmas"
      ],
      "firstSeen": "2026-07-03",
      "daysLeft": 2
    },
    {
      "type": "book",
      "title": "Nevhodný letní románek",
      "author": "Ali Hazelwood",
      "cover": "https://www.knihydobrovsky.cz/thumbs/og-image/mod_eshop/produkty/n/nevhodny-letni-romanek-20260423101738-9788024959535.jpg",
      "rating": 83,
      "ratingSource": "databazeknih.cz",
      "link": "https://www.databazeknih.cz/prehled-knihy/nevhodny-letni-romanek-586599",
      "price": 402,
      "priceShop": "Dobrovský",
      "cat": [
        "Dobrovský"
      ],
      "firstSeen": "2026-07-03",
      "daysLeft": 2
    },
    {
      "type": "movie",
      "title": "Odyssea",
      "year": "2026",
      "rating": null,
      "poster": "https://image.pmgstatic.com/cache/resized/w936/files/images/film/photos/171/263/171263768_sbmm77.jpg",
      "url": "https://www.csfd.cz/film/1580037-odyssea/prehled/",
      "genres": [
        "Akční",
        "Dobrodružný"
      ],
      "country": "USA / Velká Británie",
      "vod": [
        "Kino"
      ],
      "csfdType": "film",
      "firstSeen": "2026-07-03",
      "daysLeft": 2
    },
    {
      "type": "series",
      "title": "Nejhorší sousedi",
      "year": "2026",
      "rating": 74,
      "poster": "https://image.pmgstatic.com/cache/resized/w936/files/images/film/posters/171/390/171390750_akx830.jpg",
      "url": "https://www.csfd.cz/film/1866588-nejhorsi-sousedi/prehled/",
      "genres": [
        "Dokumentární",
        "Krimi"
      ],
      "country": "USA",
      "vod": [
        "Netflix"
      ],
      "csfdType": "seriál",
      "firstSeen": "2026-07-03",
      "daysLeft": 2
    },
    {
      "type": "series",
      "title": "Živá pára",
      "year": "2026",
      "rating": null,
      "poster": "https://image.pmgstatic.com/cache/resized/w936/files/images/film/posters/171/292/171292627_m7u0cx.jpg",
      "url": "https://www.csfd.cz/film/1821008-ziva-para/prehled/",
      "genres": [
        "Krimi",
        "Drama"
      ],
      "country": "Japonsko",
      "vod": [
        "Netflix"
      ],
      "csfdType": "seriál",
      "firstSeen": "2026-07-03",
      "daysLeft": 2
    },
    {
      "type": "game",
      "title": "Supermarket Chaos",
      "rating": 85,
      "reviews": 320,
      "scoreDesc": "Very Positive",
      "price": "4,67€",
      "image": "https://shared.cloudflare.steamstatic.com/store_item_assets/steam/apps/4800590/94039969cff7fbabbb048e93bd5009c1948ca2ce/header.jpg?t=1782778526",
      "url": "https://store.steampowered.com/app/4800590/",
      "tags": [
        "Nezávislé",
        "Simulátory"
      ],
      "released": "2026-06-29T00:00:00.000Z",
      "firstSeen": "2026-07-03",
      "daysLeft": 2
    },
    {
      "type": "game",
      "title": "Procelio",
      "rating": 92,
      "reviews": 40,
      "scoreDesc": "Positive",
      "price": "Zdarma",
      "image": "https://shared.cloudflare.steamstatic.com/store_item_assets/steam/apps/4173970/e1fe9a76c13c8878b69c039628b8f2825fc84536/header.jpg?t=1782864005",
      "url": "https://store.steampowered.com/app/4173970/",
      "tags": [
        "Akční",
        "Nezávislé",
        "Simulátory",
        "Free to play",
        "Předběžný přístup"
      ],
      "released": "2026-06-30T00:00:00.000Z",
      "firstSeen": "2026-07-03",
      "daysLeft": 2
    },
    {
      "type": "game",
      "title": "Antivirus Girl",
      "rating": 97,
      "reviews": 35,
      "scoreDesc": "Positive",
      "price": "7,81€",
      "image": "https://shared.cloudflare.steamstatic.com/store_item_assets/steam/apps/4156370/c52128489ec617a4a0fc5912568fd762378f3114/header.jpg?t=1782920291",
      "url": "https://store.steampowered.com/app/4156370/",
      "tags": [
        "Akční",
        "Nenáročné",
        "Nezávislé",
        "Simulátory",
        "Strategické"
      ],
      "released": "2026-07-01T00:00:00.000Z",
      "firstSeen": "2026-07-03",
      "daysLeft": 2
    },
    {
      "type": "book",
      "title": "Zajíc a já",
      "author": "Chloe Dalton",
      "cover": "https://obalky.kosmas.cz/ArticleCovers/565/510_bg.jpg",
      "rating": 68,
      "ratingSource": "databazeknih.cz",
      "link": "https://www.databazeknih.cz/prehled-knihy/joanna-zajic-v-pytli-50977",
      "price": 396,
      "priceShop": "Kosmas",
      "cat": [
        "Kosmas"
      ],
      "firstSeen": "2026-07-04",
      "daysLeft": 3
    },
    {
      "type": "book",
      "title": "Madona zabijáků",
      "author": "Fernando Vallejo",
      "cover": "https://obalky.kosmas.cz/ArticleCovers/258/604_bg.jpg",
      "rating": 70,
      "ratingSource": "databazeknih.cz",
      "link": "https://www.databazeknih.cz/prehled-knihy/madona-zabijaku-408477",
      "price": 35,
      "priceShop": "Kosmas",
      "cat": [
        "Kosmas"
      ],
      "firstSeen": "2026-07-04",
      "daysLeft": 3
    },
    {
      "type": "book",
      "title": "Na konec světa",
      "author": "Kristina Carlson",
      "cover": "https://obalky.kosmas.cz/ArticleCovers/187/409_bg.jpg",
      "rating": 78,
      "ratingSource": "databazeknih.cz",
      "link": "https://www.databazeknih.cz/prehled-knihy/na-konec-sveta-237244",
      "price": 53,
      "priceShop": "Kosmas",
      "cat": [
        "Kosmas"
      ],
      "firstSeen": "2026-07-04",
      "daysLeft": 3
    },
    {
      "type": "book",
      "title": "Na okraji světla",
      "author": "Maria Peura",
      "cover": "https://obalky.kosmas.cz/ArticleCovers/148/912_bg.jpg",
      "rating": 83,
      "ratingSource": "databazeknih.cz",
      "link": "https://www.databazeknih.cz/prehled-knihy/na-okraji-svetla-25344",
      "price": 26,
      "priceShop": "Kosmas",
      "cat": [
        "Kosmas"
      ],
      "firstSeen": "2026-07-04",
      "daysLeft": 3
    },
    {
      "type": "book",
      "title": "Zlá krev",
      "author": "Angela Marsonsová",
      "cover": "https://www.knihydobrovsky.cz/thumbs/og-image/mod_eshop/produkty/z/zla-krev-20260401153655-9788028416676.jpg",
      "rating": 74,
      "ratingSource": "databazeknih.cz",
      "link": "https://www.databazeknih.cz/prehled-knihy/alexandra-cooperova-zla-krev-4438",
      "price": 447,
      "priceShop": "Dobrovský",
      "cat": [
        "Dobrovský"
      ],
      "firstSeen": "2026-07-04",
      "daysLeft": 3
    },
    {
      "type": "book",
      "title": "Siddhártha",
      "author": "Hermann Hesse",
      "cover": "https://obalky.kosmas.cz/ArticleCovers/104/483_bg.jpg",
      "rating": 90,
      "ratingSource": "databazeknih.cz",
      "link": "https://www.databazeknih.cz/prehled-knihy/siddhartha-11241",
      "price": 223,
      "priceShop": "Kosmas",
      "cat": [
        "Kosmas"
      ],
      "firstSeen": "2026-07-04",
      "daysLeft": 3
    },
    {
      "type": "series",
      "title": "Silo - Season 3",
      "year": "2026",
      "rating": 76,
      "poster": "https://image.pmgstatic.com/cache/resized/w936/files/images/film/posters/171/223/171223789_nftijk.png",
      "url": "https://www.csfd.cz/film/1324435-silo/1622608-season-3/prehled/",
      "genres": [
        "Sci-Fi",
        "Drama"
      ],
      "country": "USA",
      "vod": [
        "Apple TV+"
      ],
      "csfdType": "seriál",
      "firstSeen": "2026-07-04",
      "daysLeft": 3
    },
    {
      "type": "series",
      "title": "Silo",
      "year": "2023",
      "rating": 83,
      "poster": "https://image.pmgstatic.com/cache/resized/w936/files/images/film/posters/171/427/171427764_w14797.jpg",
      "url": "https://www.csfd.cz/film/1324435-silo/prehled/",
      "genres": [
        "Sci-Fi",
        "Drama"
      ],
      "country": "USA",
      "vod": [
        "Apple TV+"
      ],
      "csfdType": "seriál",
      "firstSeen": "2026-07-04",
      "daysLeft": 3
    },
    {
      "type": "game",
      "title": "Master Healer Kale with useless party",
      "rating": 97,
      "reviews": 143,
      "scoreDesc": "Very Positive",
      "price": "3,32€",
      "image": "https://shared.cloudflare.steamstatic.com/store_item_assets/steam/apps/4634490/088b9ab009bb95af23d5e8662ad572c38aad14f0/header.jpg?t=1783051217",
      "url": "https://store.steampowered.com/app/4634490/",
      "tags": [
        "Nezávislé",
        "RPG",
        "Strategické"
      ],
      "released": "2026-07-02T00:00:00.000Z",
      "firstSeen": "2026-07-04",
      "daysLeft": 3
    }
  ],
  "counts": {
    "books": 30,
    "movies": 3,
    "series": 5,
    "games": 5
  }
}